dbgprint/__init__.py
dbgprint-1.0.8.dist-info/LICENSE
dbgprint-1.0.8.dist-info/METADATA
dbgprint-1.0.8.dist-info/WHEEL
dbgprint-1.0.8.dist-info/top_level.txt
dbgprint-1.0.8.dist-info/RECORD
